opencmiss2cmlibs.py
upgradeargondocuments.py
libocm2cml/Grammar.txt
libocm2cml/PatternGrammar.txt
libocm2cml/__init__.py
libocm2cml/btm_matcher.py
libocm2cml/btm_utils.py
libocm2cml/fixer_base.py
libocm2cml/fixer_util.py
libocm2cml/patcomp.py
libocm2cml/pygram.py
libocm2cml/pytree.py
libocm2cml/refactor.py
libocm2cml/fixes/__init__.py
libocm2cml/fixes/fix_imports.py
libocm2cml/pgen2/__init__.py
libocm2cml/pgen2/driver.py
libocm2cml/pgen2/grammar.py
libocm2cml/pgen2/literals.py
libocm2cml/pgen2/parse.py
libocm2cml/pgen2/pgen.py
libocm2cml/pgen2/token.py
libocm2cml/pgen2/tokenize.py
opencmiss2cmlibs-0.1.6.dist-info/LICENSE
opencmiss2cmlibs-0.1.6.dist-info/METADATA
opencmiss2cmlibs-0.1.6.dist-info/WHEEL
opencmiss2cmlibs-0.1.6.dist-info/entry_points.txt
opencmiss2cmlibs-0.1.6.dist-info/top_level.txt
opencmiss2cmlibs-0.1.6.dist-info/RECORD
