Metadata-Version: 2.1
Name: opencmiss2cmlibs
Version: 0.1.6
Summary: Application converting packages that use OpenCMISS-Zinc to CMLibs Zinc.
License: Apache Software License
Keywords: continuum modelling
Classifier: Development Status :: 4 - Beta
Classifier: License :: OSI Approved :: Apache Software License
Classifier: Programming Language :: Python :: 3
Classifier: Programming Language :: Python :: 3.9
License-File: LICENSE
